lxzbiotools/__init__.py
lxzbiotools/lxzbiotools.py
lxzbiotools/plot.py
lxzbiotools/plot_1.py
lxzbiotools/utils.py
lxzbiotools-0.5.5.dist-info/entry_points.txt
lxzbiotools-0.5.5.dist-info/WHEEL
lxzbiotools-0.5.5.dist-info/METADATA
lxzbiotools-0.5.5.dist-info/RECORD
