Metadata-Version: 2.1
Name: lxzbiotools
Version: 0.5.5
Summary: Xingze Li's Bioinformatics Analysis Tools
Author: Xingze_Li
Author-email: lixingzee@gmail.com
Requires-Python: >=3.6,<4.0
Classifier: Programming Language :: Python :: 3
Classifier: Programming Language :: Python :: 3.6
Classifier: Programming Language :: Python :: 3.7
Classifier: Programming Language :: Python :: 3.8
Classifier: Programming Language :: Python :: 3.9
Classifier: Programming Language :: Python :: 3.10
Requires-Dist: biopython (>=1.79,<2.0)
Requires-Dist: matplotlib (>=3.6.0,<4.0.0)
Requires-Dist: openpyxl (>=3.0.10,<4.0.0)
Requires-Dist: pandas (>=1.4.4,<2.0.0)
Requires-Dist: pathlib (>=1.0.1,<2.0.0)
Requires-Dist: rich (>=12.5.1,<13.0.0)
Requires-Dist: typer (>=0.6.1,<0.7.0)
